setup.py
wayround_org/xmpp/__init__.py
wayround_org/xmpp/adhoc.py
wayround_org/xmpp/bob.py
wayround_org/xmpp/captcha.py
wayround_org/xmpp/client.py
wayround_org/xmpp/client_bot.py
wayround_org/xmpp/core.py
wayround_org/xmpp/datetime.py
wayround_org/xmpp/delay.py
wayround_org/xmpp/disco.py
wayround_org/xmpp/muc.py
wayround_org/xmpp/oob.py
wayround_org/xmpp/privacy.py
wayround_org/xmpp/registration.py
wayround_org/xmpp/xcard_4.py
wayround_org/xmpp/xcard_temp.py
wayround_org/xmpp/xdata.py
wayround_org/xmpp/xdata_media_element.py
wayround_org_xmpp.egg-info/PKG-INFO
wayround_org_xmpp.egg-info/SOURCES.txt
wayround_org_xmpp.egg-info/dependency_links.txt
wayround_org_xmpp.egg-info/requires.txt
wayround_org_xmpp.egg-info/top_level.txt