Metadata-Version: 1.1
Name: wayround-org-xmpp
Version: 0.8.1
Summary: XMPP protocol implementation
Home-page: https://github.com/AnimusPEXUS/wayround_org_xmpp
Author: Alexey V Gorshkov
Author-email: animus@wayround.org
License: UNKNOWN
Platform: UNKNOWN
Classifier: License :: OSI Approved :: GNU General Public License v3 or later (GPLv3+)
Classifier: Operating System :: POSIX
